[
  {
    "Matrícula": "00324795 / 1",
    "Tipo da Folha": "Folha Mensal",
    "Nome": "Adilton Batista Campos",
    "Cargo": "Tecnico de Aparelho Gessado",
    "Vínculo Empregatício": "CONTRATADO",
    "Salário Base": 1902.84,
    "Proventos": 2565.43,
    "Vantagens": 0,
    "Vencimentos Totais": 2565.43,
    "Descontos": 289.6,
    "Líquido": 2275.83
  },
  {
    "Matrícula": "00324922 / 1",
    "Tipo da Folha": "Folha Mensal",
    "Nome": "Alessandra Goncalves da Silva Gomes",
    "Cargo": "Agente Administrativo",
    "Vínculo Empregatício": "CONTRATADO",
    "Salário Base": 1902.84,
    "Proventos": 2550.84,
    "Vantagens": 0,
    "Vencimentos Totais": 2550.84,
    "Descontos": 167.01,
    "Líquido": 2383.83
  },
  {
    "Matrícula": "00320994 / 1",
    "Tipo da Folha": "Rescisão",
    "Nome": "Alessandro da Silva",
    "Cargo": "Agente de Combate as Endemias",
    "Vínculo Empregatício": "CONTRATADO",
    "Salário Base": 0.0,
    "Proventos": 9707.57,
    "Vantagens": 0,
    "Vencimentos Totais": 9707.57,
    "Descontos": 608.87,
    "Líquido": 9098.7
  },
  {
    "Matrícula": "00320820 / 1",
    "Tipo da Folha": "Folha Mensal",
    "Nome": "Alexandre Cordeiro de Barros",
    "Cargo": "Agente de Combate as Endemias",
    "Vínculo Empregatício": "CONTRATADO",
    "Salário Base": 3242.0,
    "Proventos": 4610.4,
    "Vantagens": 0,
    "Vencimentos Totais": 4610.4,
    "Descontos": 355.43,
    "Líquido": 4254.97
  },
  {
    "Matrícula": "00321389 / 1",
    "Tipo da Folha": "Folha Mensal",
    "Nome": "Alexandre Guilherme Silva",
    "Cargo": "Agente de Combate as Endemias",
    "Vínculo Empregatício": "CONTRATADO",
    "Salário Base": 3242.0,
    "Proventos": 4646.4,
    "Vantagens": 0,
    "Vencimentos Totais": 4646.4,
    "Descontos": 355.43,
    "Líquido": 4290.97
  },
  {
    "Matrícula": "00322431 / 1",
    "Tipo da Folha": "Folha Mensal",
    "Nome": "Aline Bessa de Souza",
    "Cargo": "Agente Administrativo",
    "Vínculo Empregatício": "CONTRATADO",
    "Salário Base": 1902.84,
    "Proventos": 2316.84,
    "Vantagens": 0,
    "Vencimentos Totais": 2316.84,
    "Descontos": 181.56,
    "Líquido": 2135.28
  },
  {
    "Matrícula": "00327018 / 1",
    "Tipo da Folha": "Folha Mensal",
    "Nome": "Aline Cristina Barboza Pontes Lira",
    "Cargo": "Entrevistador Social",
    "Vínculo Empregatício": "CONTRATADO",
    "Salário Base": 1621.0,
    "Proventos": 1566.97,
    "Vantagens": 0,
    "Vencimentos Totais": 1566.97,
    "Descontos": 117.52,
    "Líquido": 1449.45
  },
  {
    "Matrícula": "00321370 / 1",
    "Tipo da Folha": "Folha Mensal",
    "Nome": "Aline Cristini Andrade de Souza",
    "Cargo": "Agente de Combate as Endemias",
    "Vínculo Empregatício": "CONTRATADO",
    "Salário Base": 3242.0,
    "Proventos": 4592.4,
    "Vantagens": 0,
    "Vencimentos Totais": 4592.4,
    "Descontos": 355.43,
    "Líquido": 4236.97
  },
  {
    "Matrícula": "00324965 / 1",
    "Tipo da Folha": "Folha Mensal",
    "Nome": "Ana Lucia de Macedo Asth Marques",
    "Cargo": "Agente Administrativo",
    "Vínculo Empregatício": "CONTRATADO",
    "Salário Base": 1902.84,
    "Proventos": 2620.92,
    "Vantagens": 0,
    "Vencimentos Totais": 2620.92,
    "Descontos": 146.93,
    "Líquido": 2473.99
  },
  {
    "Matrícula": "00321290 / 1",
    "Tipo da Folha": "Folha Mensal",
    "Nome": "Ana Lucia Madureira da Silva",
    "Cargo": "Agente de Combate as Endemias",
    "Vínculo Empregatício": "CONTRATADO",
    "Salário Base": 3242.0,
    "Proventos": 4646.4,
    "Vantagens": 0,
    "Vencimentos Totais": 4646.4,
    "Descontos": 355.43,
    "Líquido": 4290.97
  },
  {
    "Matrícula": "00320935 / 1",
    "Tipo da Folha": "Rescisão",
    "Nome": "Andre Silva Costa",
    "Cargo": "Agente de Combate as Endemias",
    "Vínculo Empregatício": "CONTRATADO",
    "Salário Base": 0.0,
    "Proventos": 9725.6,
    "Vantagens": 0,
    "Vencimentos Totais": 9725.6,
    "Descontos": 404.23,
    "Líquido": 9321.37
  },
  {
    "Matrícula": "00325015 / 1",
    "Tipo da Folha": "Folha Mensal",
    "Nome": "Andrea Alice Alves Franco",
    "Cargo": "Enfermeiro do Trabalho",
    "Vínculo Empregatício": "CONTRATADO",
    "Salário Base": 5578.85,
    "Proventos": 6860.24,
    "Vantagens": 0,
    "Vencimentos Totais": 6860.24,
    "Descontos": 940.11,
    "Líquido": 5920.13
  },
  {
    "Matrícula": "00316431 / 2",
    "Tipo da Folha": "Folha Mensal",
    "Nome": "Andrea Borba Ribeiro Dore",
    "Cargo": "Agente Administrativo",
    "Vínculo Empregatício": "CONTRATADO",
    "Salário Base": 1902.84,
    "Proventos": 2620.92,
    "Vantagens": 0,
    "Vencimentos Totais": 2620.92,
    "Descontos": 172.03,
    "Líquido": 2448.89
  },
  {
    "Matrícula": "00320943 / 1",
    "Tipo da Folha": "Folha Mensal",
    "Nome": "Andrea da Silva Costa de Souza",
    "Cargo": "Agente de Combate as Endemias",
    "Vínculo Empregatício": "CONTRATADO",
    "Salário Base": 3242.0,
    "Proventos": 4592.4,
    "Vantagens": 0,
    "Vencimentos Totais": 4592.4,
    "Descontos": 355.43,
    "Líquido": 4236.97
  },
  {
    "Matrícula": "00321400 / 1",
    "Tipo da Folha": "Folha Mensal",
    "Nome": "Andrea Regina da Silva Conceicao",
    "Cargo": "Agente de Combate as Endemias",
    "Vínculo Empregatício": "CONTRATADO",
    "Salário Base": 3242.0,
    "Proventos": 5027.59,
    "Vantagens": 0,
    "Vencimentos Totais": 5027.59,
    "Descontos": 2029.3,
    "Líquido": 2998.29
  },
  {
    "Matrícula": "00326488 / 1",
    "Tipo da Folha": "Folha Mensal",
    "Nome": "Andreia Avelina Rosa Lopes",
    "Cargo": "Aux. de Desenv. Infantil",
    "Vínculo Empregatício": "CONTRATADO",
    "Salário Base": 1621.0,
    "Proventos": 2038.19,
    "Vantagens": 0,
    "Vencimentos Totais": 2038.19,
    "Descontos": 1127.43,
    "Líquido": 910.76
  },
  {
    "Matrícula": "00324027 / 1",
    "Tipo da Folha": "Folha Mensal",
    "Nome": "Andrey Martins Domingos de Almeida",
    "Cargo": "Agente de Combate as Endemias",
    "Vínculo Empregatício": "CONTRATADO",
    "Salário Base": 3242.0,
    "Proventos": 5027.59,
    "Vantagens": 0,
    "Vencimentos Totais": 5027.59,
    "Descontos": 355.43,
    "Líquido": 4672.16
  },
  {
    "Matrícula": "00320722 / 1",
    "Tipo da Folha": "Folha Mensal",
    "Nome": "Anselmo Luiz de Jesus",
    "Cargo": "Agente de Combate as Endemias",
    "Vínculo Empregatício": "CONTRATADO",
    "Salário Base": 3242.0,
    "Proventos": 4592.4,
    "Vantagens": 0,
    "Vencimentos Totais": 4592.4,
    "Descontos": 355.43,
    "Líquido": 4236.97
  },
  {
    "Matrícula": "00325023 / 1",
    "Tipo da Folha": "Folha Mensal",
    "Nome": "Breno Luzente Costa de Oliveira",
    "Cargo": "Agente de Combate as Endemias",
    "Vínculo Empregatício": "CONTRATADO",
    "Salário Base": 3242.0,
    "Proventos": 4235.19,
    "Vantagens": 0,
    "Vencimentos Totais": 4235.19,
    "Descontos": 1055.11,
    "Líquido": 3180.08
  },
  {
    "Matrícula": "00320960 / 1",
    "Tipo da Folha": "Folha Mensal",
    "Nome": "Camila Nunes dos Santos",
    "Cargo": "Agente de Combate as Endemias",
    "Vínculo Empregatício": "CONTRATADO",
    "Salário Base": 3242.0,
    "Proventos": 5027.59,
    "Vantagens": 0,
    "Vencimentos Totais": 5027.59,
    "Descontos": 1220.32,
    "Líquido": 3807.27
  },
  {
    "Matrícula": "00320951 / 1",
    "Tipo da Folha": "Folha Mensal",
    "Nome": "Carla do Rosario Martins",
    "Cargo": "Agente de Combate as Endemias",
    "Vínculo Empregatício": "CONTRATADO",
    "Salário Base": 3242.0,
    "Proventos": 5009.59,
    "Vantagens": 0,
    "Vencimentos Totais": 5009.59,
    "Descontos": 1361.29,
    "Líquido": 3648.3
  },
  {
    "Matrícula": "00324949 / 1",
    "Tipo da Folha": "Folha Mensal",
    "Nome": "Carla Mara Calixto Monteiro da Silva Neves",
    "Cargo": "Agente Administrativo",
    "Vínculo Empregatício": "CONTRATADO",
    "Salário Base": 1902.84,
    "Proventos": 2550.84,
    "Vantagens": 0,
    "Vencimentos Totais": 2550.84,
    "Descontos": 146.93,
    "Líquido": 2403.91
  },
  {
    "Matrícula": "00318990 / 1",
    "Tipo da Folha": "Folha Mensal",
    "Nome": "Carla Paura Layo Guimaraes",
    "Cargo": "Auxiliar de Secretaria Escolar",
    "Vínculo Empregatício": "CONTRATADO",
    "Salário Base": 1621.0,
    "Proventos": 2341.0,
    "Vantagens": 0,
    "Vencimentos Totais": 2341.0,
    "Descontos": 121.57,
    "Líquido": 2219.43
  },
  {
    "Matrícula": "00321990 / 1",
    "Tipo da Folha": "Folha Mensal",
    "Nome": "Carlos Henriques da Silveira Silva",
    "Cargo": "Agente de Combate as Endemias",
    "Vínculo Empregatício": "CONTRATADO",
    "Salário Base": 3242.0,
    "Proventos": 6711.57,
    "Vantagens": 0,
    "Vencimentos Totais": 6711.57,
    "Descontos": 583.99,
    "Líquido": 6127.58
  },
  {
    "Matrícula": "00326356 / 1",
    "Tipo da Folha": "Folha Mensal",
    "Nome": "Caroline Rodrigues Salles",
    "Cargo": "Secretario Escolar",
    "Vínculo Empregatício": "CONTRATADO",
    "Salário Base": 1902.84,
    "Proventos": 3081.16,
    "Vantagens": 0,
    "Vencimentos Totais": 3081.16,
    "Descontos": 146.93,
    "Líquido": 2934.23
  },
  {
    "Matrícula": "00326445 / 1",
    "Tipo da Folha": "Folha Mensal",
    "Nome": "Cassiana da Silva Goncalves Machado",
    "Cargo": "Aux. de Desenv. Infantil",
    "Vínculo Empregatício": "CONTRATADO",
    "Salário Base": 1621.0,
    "Proventos": 1691.08,
    "Vantagens": 0,
    "Vencimentos Totais": 1691.08,
    "Descontos": 121.57,
    "Líquido": 1569.51
  },
  {
    "Matrícula": "00321133 / 1",
    "Tipo da Folha": "Folha Mensal",
    "Nome": "Cassiane Souza de Carvalho",
    "Cargo": "Agente de Combate as Endemias",
    "Vínculo Empregatício": "CONTRATADO",
    "Salário Base": 3242.0,
    "Proventos": 4538.4,
    "Vantagens": 0,
    "Vencimentos Totais": 4538.4,
    "Descontos": 355.43,
    "Líquido": 4182.97
  },
  {
    "Matrícula": "00327026 / 1",
    "Tipo da Folha": "Folha Mensal",
    "Nome": "Catia Faria dos Santos de Barros",
    "Cargo": "Entrevistador Social",
    "Vínculo Empregatício": "CONTRATADO",
    "Salário Base": 1621.0,
    "Proventos": 1566.97,
    "Vantagens": 0,
    "Vencimentos Totais": 1566.97,
    "Descontos": 117.52,
    "Líquido": 1449.45
  },
  {
    "Matrícula": "00321249 / 1",
    "Tipo da Folha": "Folha Mensal",
    "Nome": "Cediolaine Azeredo Ramos",
    "Cargo": "Agente de Combate as Endemias",
    "Vínculo Empregatício": "CONTRATADO",
    "Salário Base": 3242.0,
    "Proventos": 5063.59,
    "Vantagens": 0,
    "Vencimentos Totais": 5063.59,
    "Descontos": 1667.65,
    "Líquido": 3395.94
  },
  {
    "Matrícula": "00322105 / 1",
    "Tipo da Folha": "Folha Mensal",
    "Nome": "Cilene Coutinho",
    "Cargo": "Agente de Combate as Endemias",
    "Vínculo Empregatício": "CONTRATADO",
    "Salário Base": 3242.0,
    "Proventos": 5063.59,
    "Vantagens": 0,
    "Vencimentos Totais": 5063.59,
    "Descontos": 355.43,
    "Líquido": 4708.16
  },
  {
    "Matrícula": "00327034 / 1",
    "Tipo da Folha": "Folha Mensal",
    "Nome": "Claudia de Jesus Mello Oliveira",
    "Cargo": "Entrevistador Social",
    "Vínculo Empregatício": "CONTRATADO",
    "Salário Base": 1621.0,
    "Proventos": 1566.97,
    "Vantagens": 0,
    "Vencimentos Totais": 1566.97,
    "Descontos": 117.52,
    "Líquido": 1449.45
  },
  {
    "Matrícula": "00321192 / 1",
    "Tipo da Folha": "Folha Mensal",
    "Nome": "Claudia Lima Teodoro",
    "Cargo": "Agente de Combate as Endemias",
    "Vínculo Empregatício": "CONTRATADO",
    "Salário Base": 3242.0,
    "Proventos": 4610.4,
    "Vantagens": 0,
    "Vencimentos Totais": 4610.4,
    "Descontos": 355.43,
    "Líquido": 4254.97
  },
  {
    "Matrícula": "00323926 / 1",
    "Tipo da Folha": "Folha Mensal",
    "Nome": "Claudio de Oliveira Dias",
    "Cargo": "Motorista",
    "Vínculo Empregatício": "CONTRATADO",
    "Salário Base": 1621.0,
    "Proventos": 4817.66,
    "Vantagens": 0,
    "Vencimentos Totais": 4817.66,
    "Descontos": 221.43,
    "Líquido": 4596.23
  },
  {
    "Matrícula": "00321184 / 1",
    "Tipo da Folha": "Folha Mensal",
    "Nome": "Creuza Balduino da Silva",
    "Cargo": "Agente de Combate as Endemias",
    "Vínculo Empregatício": "CONTRATADO",
    "Salário Base": 3242.0,
    "Proventos": 4610.4,
    "Vantagens": 0,
    "Vencimentos Totais": 4610.4,
    "Descontos": 355.43,
    "Líquido": 4254.97
  },
  {
    "Matrícula": "00324566 / 1",
    "Tipo da Folha": "Folha Mensal",
    "Nome": "Cristiane Souza da Silva",
    "Cargo": "Tecnico de Aparelho Gessado",
    "Vínculo Empregatício": "CONTRATADO",
    "Salário Base": 1902.84,
    "Proventos": 2565.43,
    "Vantagens": 0,
    "Vencimentos Totais": 2565.43,
    "Descontos": 306.48,
    "Líquido": 2258.95
  },
  {
    "Matrícula": "00326941 / 1",
    "Tipo da Folha": "Folha Mensal",
    "Nome": "Cristina dos Santos Ribeiro",
    "Cargo": "Entrevistador Social",
    "Vínculo Empregatício": "CONTRATADO",
    "Salário Base": 1621.0,
    "Proventos": 1566.97,
    "Vantagens": 0,
    "Vencimentos Totais": 1566.97,
    "Descontos": 117.52,
    "Líquido": 1449.45
  },
  {
    "Matrícula": "00321923 / 1",
    "Tipo da Folha": "Folha Mensal",
    "Nome": "Daiana de Souza Pereira da Conceicao",
    "Cargo": "Agente de Combate as Endemias",
    "Vínculo Empregatício": "CONTRATADO",
    "Salário Base": 3242.0,
    "Proventos": 5063.59,
    "Vantagens": 0,
    "Vencimentos Totais": 5063.59,
    "Descontos": 1657.61,
    "Líquido": 3405.98
  },
  {
    "Matrícula": "00320978 / 1",
    "Tipo da Folha": "Folha Mensal",
    "Nome": "Daniel Fernandes de Castro",
    "Cargo": "Agente de Combate as Endemias",
    "Vínculo Empregatício": "CONTRATADO",
    "Salário Base": 3242.0,
    "Proventos": 4610.4,
    "Vantagens": 0,
    "Vencimentos Totais": 4610.4,
    "Descontos": 355.43,
    "Líquido": 4254.97
  },
  {
    "Matrícula": "00321087 / 1",
    "Tipo da Folha": "Folha Mensal",
    "Nome": "Daniela Freire de Souza",
    "Cargo": "Agente de Combate as Endemias",
    "Vínculo Empregatício": "CONTRATADO",
    "Salário Base": 3242.0,
    "Proventos": 4991.59,
    "Vantagens": 0,
    "Vencimentos Totais": 4991.59,
    "Descontos": 1381.37,
    "Líquido": 3610.22
  },
  {
    "Matrícula": "00326950 / 1",
    "Tipo da Folha": "Folha Mensal",
    "Nome": "Daniele Silva de Souza",
    "Cargo": "Entrevistador Social",
    "Vínculo Empregatício": "CONTRATADO",
    "Salário Base": 1621.0,
    "Proventos": 1566.97,
    "Vantagens": 0,
    "Vencimentos Totais": 1566.97,
    "Descontos": 117.52,
    "Líquido": 1449.45
  },
  {
    "Matrícula": "00321362 / 1",
    "Tipo da Folha": "Folha Mensal",
    "Nome": "Denise de Souza Leal",
    "Cargo": "Agente de Combate as Endemias",
    "Vínculo Empregatício": "CONTRATADO",
    "Salário Base": 3242.0,
    "Proventos": 4484.4,
    "Vantagens": 0,
    "Vencimentos Totais": 4484.4,
    "Descontos": 355.43,
    "Líquido": 4128.97
  },
  {
    "Matrícula": "00325031 / 1",
    "Tipo da Folha": "Folha Mensal",
    "Nome": "Denise Jose de Mello",
    "Cargo": "Agente Administrativo",
    "Vínculo Empregatício": "CONTRATADO",
    "Salário Base": 1902.84,
    "Proventos": 2658.84,
    "Vantagens": 0,
    "Vencimentos Totais": 2658.84,
    "Descontos": 146.93,
    "Líquido": 2511.91
  },
  {
    "Matrícula": "00326925 / 1",
    "Tipo da Folha": "Folha Mensal",
    "Nome": "Denise Pereira Carvalho Lucio",
    "Cargo": "Entrevistador Social",
    "Vínculo Empregatício": "CONTRATADO",
    "Salário Base": 1621.0,
    "Proventos": 1566.97,
    "Vantagens": 0,
    "Vencimentos Totais": 1566.97,
    "Descontos": 117.52,
    "Líquido": 1449.45
  },
  {
    "Matrícula": "00320927 / 1",
    "Tipo da Folha": "Folha Mensal",
    "Nome": "Edenilca Alves de Souza",
    "Cargo": "Agente de Combate as Endemias",
    "Vínculo Empregatício": "CONTRATADO",
    "Salário Base": 3242.0,
    "Proventos": 4538.4,
    "Vantagens": 0,
    "Vencimentos Totais": 4538.4,
    "Descontos": 355.43,
    "Líquido": 4182.97
  },
  {
    "Matrícula": "00320919 / 1",
    "Tipo da Folha": "Folha Mensal",
    "Nome": "Edilene Soares de Araujo",
    "Cargo": "Agente de Combate as Endemias",
    "Vínculo Empregatício": "CONTRATADO",
    "Salário Base": 3242.0,
    "Proventos": 4646.4,
    "Vantagens": 0,
    "Vencimentos Totais": 4646.4,
    "Descontos": 355.43,
    "Líquido": 4290.97
  },
  {
    "Matrícula": "00320897 / 1",
    "Tipo da Folha": "Rescisão",
    "Nome": "Edison Ximenes Araujo de Melo",
    "Cargo": "Agente de Combate as Endemias",
    "Vínculo Empregatício": "CONTRATADO",
    "Salário Base": 0.0,
    "Proventos": 9833.6,
    "Vantagens": 0,
    "Vencimentos Totais": 9833.6,
    "Descontos": 326.25,
    "Líquido": 9507.35
  },
  {
    "Matrícula": "00320900 / 1",
    "Tipo da Folha": "Folha Mensal",
    "Nome": "Edmilson Severino da Silva",
    "Cargo": "Agente de Combate as Endemias",
    "Vínculo Empregatício": "CONTRATADO",
    "Salário Base": 3242.0,
    "Proventos": 4610.4,
    "Vantagens": 0,
    "Vencimentos Totais": 4610.4,
    "Descontos": 355.43,
    "Líquido": 4254.97
  },
  {
    "Matrícula": "00320889 / 1",
    "Tipo da Folha": "Folha Mensal",
    "Nome": "Eduardo Gomes da Silva",
    "Cargo": "Agente de Combate as Endemias",
    "Vínculo Empregatício": "CONTRATADO",
    "Salário Base": 3242.0,
    "Proventos": 4610.4,
    "Vantagens": 0,
    "Vencimentos Totais": 4610.4,
    "Descontos": 355.43,
    "Líquido": 4254.97
  },
  {
    "Matrícula": "00322865 / 1",
    "Tipo da Folha": "Folha Mensal",
    "Nome": "Eduardo Silva de Oliveira",
    "Cargo": "Agente de Combate as Endemias",
    "Vínculo Empregatício": "CONTRATADO",
    "Salário Base": 3242.0,
    "Proventos": 4912.36,
    "Vantagens": 0,
    "Vencimentos Totais": 4912.36,
    "Descontos": 1374.39,
    "Líquido": 3537.97
  },
  {
    "Matrícula": "00327069 / 1",
    "Tipo da Folha": "Folha Complementar (02/2026)",
    "Nome": "Elen Carla da Cruz Lopes",
    "Cargo": "Entrevistador Social",
    "Vínculo Empregatício": "CONTRATADO",
    "Salário Base": 0.0,
    "Proventos": 432.26,
    "Vantagens": 0,
    "Vencimentos Totais": 432.26,
    "Descontos": 32.41,
    "Líquido": 399.85
  },
  {
    "Matrícula": "00320447 / 2",
    "Tipo da Folha": "Rescisão",
    "Nome": "Elenice Correa Cota",
    "Cargo": "Professor I - 30 Horas",
    "Vínculo Empregatício": "CONTRATADO",
    "Salário Base": 0.0,
    "Proventos": 894.74,
    "Vantagens": 0,
    "Vencimentos Totais": 894.74,
    "Descontos": 894.74,
    "Líquido": 0.0
  },
  {
    "Matrícula": "00320870 / 1",
    "Tipo da Folha": "Folha Mensal",
    "Nome": "Elenita Geremias de Souza Soares",
    "Cargo": "Agente de Combate as Endemias",
    "Vínculo Empregatício": "CONTRATADO",
    "Salário Base": 3242.0,
    "Proventos": 4574.4,
    "Vantagens": 0,
    "Vencimentos Totais": 4574.4,
    "Descontos": 355.43,
    "Líquido": 4218.97
  },
  {
    "Matrícula": "00321001 / 1",
    "Tipo da Folha": "Folha Mensal",
    "Nome": "Elia Santos Gomes",
    "Cargo": "Agente de Combate as Endemias",
    "Vínculo Empregatício": "CONTRATADO",
    "Salário Base": 3242.0,
    "Proventos": 4610.4,
    "Vantagens": 0,
    "Vencimentos Totais": 4610.4,
    "Descontos": 355.43,
    "Líquido": 4254.97
  },
  {
    "Matrícula": "00327050 / 1",
    "Tipo da Folha": "Folha Mensal",
    "Nome": "Eliana Costa Alves Martins",
    "Cargo": "Entrevistador Social",
    "Vínculo Empregatício": "CONTRATADO",
    "Salário Base": 1621.0,
    "Proventos": 1566.97,
    "Vantagens": 0,
    "Vencimentos Totais": 1566.97,
    "Descontos": 117.52,
    "Líquido": 1449.45
  },
  {
    "Matrícula": "00320986 / 1",
    "Tipo da Folha": "Folha Mensal",
    "Nome": "Eliane Martins Moreira",
    "Cargo": "Agente de Combate as Endemias",
    "Vínculo Empregatício": "CONTRATADO",
    "Salário Base": 3242.0,
    "Proventos": 4646.4,
    "Vantagens": 0,
    "Vencimentos Totais": 4646.4,
    "Descontos": 355.43,
    "Líquido": 4290.97
  },
  {
    "Matrícula": "00326917 / 1",
    "Tipo da Folha": "Folha Mensal",
    "Nome": "Elielma Pinheiro Batista",
    "Cargo": "Entrevistador Social",
    "Vínculo Empregatício": "CONTRATADO",
    "Salário Base": 1621.0,
    "Proventos": 1566.97,
    "Vantagens": 0,
    "Vencimentos Totais": 1566.97,
    "Descontos": 117.52,
    "Líquido": 1449.45
  },
  {
    "Matrícula": "00321257 / 1",
    "Tipo da Folha": "Folha Mensal",
    "Nome": "Elieze Domingos dos Santos Junior",
    "Cargo": "Agente de Combate as Endemias",
    "Vínculo Empregatício": "CONTRATADO",
    "Salário Base": 3242.0,
    "Proventos": 4480.79,
    "Vantagens": 0,
    "Vencimentos Totais": 4480.79,
    "Descontos": 447.93,
    "Líquido": 4032.86
  },
  {
    "Matrícula": "00321095 / 1",
    "Tipo da Folha": "Folha Mensal",
    "Nome": "Eline Carvalho do Nascimento",
    "Cargo": "Agente de Combate as Endemias",
    "Vínculo Empregatício": "CONTRATADO",
    "Salário Base": 3242.0,
    "Proventos": 4896.4,
    "Vantagens": 0,
    "Vencimentos Totais": 4896.4,
    "Descontos": 355.43,
    "Líquido": 4540.97
  },
  {
    "Matrícula": "00324574 / 1",
    "Tipo da Folha": "Folha Mensal",
    "Nome": "Elizete Moura Oliveira Diniz de Carvalho",
    "Cargo": "Tecnico de Aparelho Gessado",
    "Vínculo Empregatício": "CONTRATADO",
    "Salário Base": 1902.84,
    "Proventos": 2498.01,
    "Vantagens": 0,
    "Vencimentos Totais": 2498.01,
    "Descontos": 204.83,
    "Líquido": 2293.18
  },
  {
    "Matrícula": "00321265 / 1",
    "Tipo da Folha": "Folha Mensal",
    "Nome": "Elizeuma Souza da Silva",
    "Cargo": "Agente de Combate as Endemias",
    "Vínculo Empregatício": "CONTRATADO",
    "Salário Base": 3242.0,
    "Proventos": 4610.4,
    "Vantagens": 0,
    "Vencimentos Totais": 4610.4,
    "Descontos": 355.43,
    "Líquido": 4254.97
  },
  {
    "Matrícula": "00321150 / 1",
    "Tipo da Folha": "Folha Mensal",
    "Nome": "Enilza Souza da Silva",
    "Cargo": "Agente de Combate as Endemias",
    "Vínculo Empregatício": "CONTRATADO",
    "Salário Base": 3242.0,
    "Proventos": 4484.4,
    "Vantagens": 0,
    "Vencimentos Totais": 4484.4,
    "Descontos": 355.43,
    "Líquido": 4128.97
  },
  {
    "Matrícula": "00320714 / 1",
    "Tipo da Folha": "Folha Mensal",
    "Nome": "Euzeli da Silveira Silva",
    "Cargo": "Agente de Combate as Endemias",
    "Vínculo Empregatício": "CONTRATADO",
    "Salário Base": 3242.0,
    "Proventos": 4592.4,
    "Vantagens": 0,
    "Vencimentos Totais": 4592.4,
    "Descontos": 355.43,
    "Líquido": 4236.97
  },
  {
    "Matrícula": "00319074 / 1",
    "Tipo da Folha": "Folha Mensal",
    "Nome": "Fabiana Gomes dos Santos Araujo",
    "Cargo": "Auxiliar de Secretaria Escolar",
    "Vínculo Empregatício": "CONTRATADO",
    "Salário Base": 1621.0,
    "Proventos": 2341.0,
    "Vantagens": 0,
    "Vencimentos Totais": 2341.0,
    "Descontos": 121.57,
    "Líquido": 2219.43
  },
  {
    "Matrícula": "00323446 / 1",
    "Tipo da Folha": "Folha Mensal",
    "Nome": "Fabio da Silva",
    "Cargo": "Motorista",
    "Vínculo Empregatício": "CONTRATADO",
    "Salário Base": 1621.0,
    "Proventos": 2411.08,
    "Vantagens": 0,
    "Vencimentos Totais": 2411.08,
    "Descontos": 121.57,
    "Líquido": 2289.51
  },
  {
    "Matrícula": "00321125 / 1",
    "Tipo da Folha": "Folha Mensal",
    "Nome": "Fabio Rodrigues Quintanilha",
    "Cargo": "Agente de Combate as Endemias",
    "Vínculo Empregatício": "CONTRATADO",
    "Salário Base": 3242.0,
    "Proventos": 4610.4,
    "Vantagens": 0,
    "Vencimentos Totais": 4610.4,
    "Descontos": 355.43,
    "Líquido": 4254.97
  },
  {
    "Matrícula": "00321117 / 1",
    "Tipo da Folha": "Folha Mensal",
    "Nome": "Fabiola Gonçalves Quintanilha",
    "Cargo": "Agente de Combate as Endemias",
    "Vínculo Empregatício": "CONTRATADO",
    "Salário Base": 3242.0,
    "Proventos": 4588.79,
    "Vantagens": 0,
    "Vencimentos Totais": 4588.79,
    "Descontos": 462.99,
    "Líquido": 4125.8
  },
  {
    "Matrícula": "00322881 / 1",
    "Tipo da Folha": "Folha Mensal",
    "Nome": "Fabricia da Silva Miguel",
    "Cargo": "Agente de Combate as Endemias",
    "Vínculo Empregatício": "CONTRATADO",
    "Salário Base": 3242.0,
    "Proventos": 4646.4,
    "Vantagens": 0,
    "Vencimentos Totais": 4646.4,
    "Descontos": 355.43,
    "Líquido": 4290.97
  },
  {
    "Matrícula": "00325058 / 1",
    "Tipo da Folha": "Folha Mensal",
    "Nome": "Fatima Aparecida Antonio",
    "Cargo": "Psicologo",
    "Vínculo Empregatício": "CONTRATADO",
    "Salário Base": 2867.61,
    "Proventos": 3623.81,
    "Vantagens": 0,
    "Vencimentos Totais": 3623.81,
    "Descontos": 271.6,
    "Líquido": 3352.21
  },
  {
    "Matrícula": "00321109 / 1",
    "Tipo da Folha": "Folha Mensal",
    "Nome": "Fernanda Rosa dos Reis",
    "Cargo": "Agente de Combate as Endemias",
    "Vínculo Empregatício": "CONTRATADO",
    "Salário Base": 3242.0,
    "Proventos": 4860.4,
    "Vantagens": 0,
    "Vencimentos Totais": 4860.4,
    "Descontos": 355.43,
    "Líquido": 4504.97
  },
  {
    "Matrícula": "00325066 / 1",
    "Tipo da Folha": "Rescisão",
    "Nome": "Flavia dos Santos Nofuentes",
    "Cargo": "Tec. em Enfermagem do Trabalho",
    "Vínculo Empregatício": "CONTRATADO",
    "Salário Base": 0.0,
    "Proventos": 2269.07,
    "Vantagens": 0,
    "Vencimentos Totais": 2269.07,
    "Descontos": 137.77,
    "Líquido": 2131.3
  },
  {
    "Matrícula": "00324760 / 1",
    "Tipo da Folha": "Folha Mensal",
    "Nome": "Gabriela Cabral Marins",
    "Cargo": "Agente Administrativo",
    "Vínculo Empregatício": "CONTRATADO",
    "Salário Base": 1902.84,
    "Proventos": 2550.84,
    "Vantagens": 0,
    "Vencimentos Totais": 2550.84,
    "Descontos": 161.99,
    "Líquido": 2388.85
  },
  {
    "Matrícula": "00325147 / 1",
    "Tipo da Folha": "Folha Mensal",
    "Nome": "Gabriela Ferreira da Silva",
    "Cargo": "Auxiliar Educacional II",
    "Vínculo Empregatício": "CONTRATADO",
    "Salário Base": 2995.73,
    "Proventos": 4810.93,
    "Vantagens": 0,
    "Vencimentos Totais": 4810.93,
    "Descontos": 1245.48,
    "Líquido": 3565.45
  },
  {
    "Matrícula": "00323802 / 1",
    "Tipo da Folha": "Folha Mensal",
    "Nome": "Gelson Francisco Pereira Lima",
    "Cargo": "Motorista",
    "Vínculo Empregatício": "CONTRATADO",
    "Salário Base": 1621.0,
    "Proventos": 2323.0,
    "Vantagens": 0,
    "Vencimentos Totais": 2323.0,
    "Descontos": 121.57,
    "Líquido": 2201.43
  },
  {
    "Matrícula": "00326372 / 1",
    "Tipo da Folha": "Folha Mensal",
    "Nome": "Gilson Cesar Pereira da Silva",
    "Cargo": "Motorista",
    "Vínculo Empregatício": "CONTRATADO",
    "Salário Base": 1621.0,
    "Proventos": 2341.0,
    "Vantagens": 0,
    "Vencimentos Totais": 2341.0,
    "Descontos": 121.57,
    "Líquido": 2219.43
  },
  {
    "Matrícula": "00324604 / 1",
    "Tipo da Folha": "Folha Mensal",
    "Nome": "Harianna Lima Marques",
    "Cargo": "Agente Administrativo",
    "Vínculo Empregatício": "CONTRATADO",
    "Salário Base": 1902.84,
    "Proventos": 2968.03,
    "Vantagens": 0,
    "Vencimentos Totais": 2968.03,
    "Descontos": 1011.82,
    "Líquido": 1956.21
  },
  {
    "Matrícula": "00321419 / 1",
    "Tipo da Folha": "Folha Mensal",
    "Nome": "Hedula Thatiana Araujo Silva",
    "Cargo": "Agente de Combate as Endemias",
    "Vínculo Empregatício": "CONTRATADO",
    "Salário Base": 3242.0,
    "Proventos": 4538.4,
    "Vantagens": 0,
    "Vencimentos Totais": 4538.4,
    "Descontos": 355.43,
    "Líquido": 4182.97
  },
  {
    "Matrícula": "00323217 / 1",
    "Tipo da Folha": "Folha Mensal",
    "Nome": "Heitor Duarte de Aguiar",
    "Cargo": "Agente de Combate as Endemias",
    "Vínculo Empregatício": "CONTRATADO",
    "Salário Base": 3242.0,
    "Proventos": 4538.4,
    "Vantagens": 0,
    "Vencimentos Totais": 4538.4,
    "Descontos": 355.43,
    "Líquido": 4182.97
  },
  {
    "Matrícula": "00321427 / 1",
    "Tipo da Folha": "Folha Mensal",
    "Nome": "Helder de Castro Pinto",
    "Cargo": "Agente de Combate as Endemias",
    "Vínculo Empregatício": "CONTRATADO",
    "Salário Base": 3242.0,
    "Proventos": 4610.4,
    "Vantagens": 0,
    "Vencimentos Totais": 4610.4,
    "Descontos": 355.43,
    "Líquido": 4254.97
  },
  {
    "Matrícula": "00327425 / 1",
    "Tipo da Folha": "Folha Complementar (02/2026)",
    "Nome": "Hosana Carla de Sousa Santos",
    "Cargo": "Entrevistador Social",
    "Vínculo Empregatício": "CONTRATADO",
    "Salário Base": 0.0,
    "Proventos": 432.26,
    "Vantagens": 0,
    "Vencimentos Totais": 432.26,
    "Descontos": 32.41,
    "Líquido": 399.85
  },
  {
    "Matrícula": "00321435 / 1",
    "Tipo da Folha": "Folha Mensal",
    "Nome": "Ismelia Fernandes Dias",
    "Cargo": "Agente de Combate as Endemias",
    "Vínculo Empregatício": "CONTRATADO",
    "Salário Base": 3242.0,
    "Proventos": 4646.4,
    "Vantagens": 0,
    "Vencimentos Totais": 4646.4,
    "Descontos": 355.43,
    "Líquido": 4290.97
  },
  {
    "Matrícula": "00323691 / 1",
    "Tipo da Folha": "Folha Mensal",
    "Nome": "Jadson Luiz Borges da Costa",
    "Cargo": "Agente Administrativo",
    "Vínculo Empregatício": "CONTRATADO",
    "Salário Base": 1902.84,
    "Proventos": 2622.84,
    "Vantagens": 0,
    "Vencimentos Totais": 2622.84,
    "Descontos": 146.93,
    "Líquido": 2475.91
  },
  {
    "Matrícula": "00321443 / 1",
    "Tipo da Folha": "Folha Mensal",
    "Nome": "Jairo de Freitas Custodio",
    "Cargo": "Agente de Combate as Endemias",
    "Vínculo Empregatício": "CONTRATADO",
    "Salário Base": 3242.0,
    "Proventos": 4610.4,
    "Vantagens": 0,
    "Vencimentos Totais": 4610.4,
    "Descontos": 355.43,
    "Líquido": 4254.97
  },
  {
    "Matrícula": "00327042 / 1",
    "Tipo da Folha": "Folha Mensal",
    "Nome": "Jamille Muniz da Silva",
    "Cargo": "Entrevistador Social",
    "Vínculo Empregatício": "CONTRATADO",
    "Salário Base": 1621.0,
    "Proventos": 1566.97,
    "Vantagens": 0,
    "Vencimentos Totais": 1566.97,
    "Descontos": 117.52,
    "Líquido": 1449.45
  },
  {
    "Matrícula": "00326909 / 1",
    "Tipo da Folha": "Folha Mensal",
    "Nome": "Janaina Rodrigues de Lima",
    "Cargo": "Entrevistador Social",
    "Vínculo Empregatício": "CONTRATADO",
    "Salário Base": 1621.0,
    "Proventos": 1566.97,
    "Vantagens": 0,
    "Vencimentos Totais": 1566.97,
    "Descontos": 117.52,
    "Líquido": 1449.45
  },
  {
    "Matrícula": "00321168 / 1",
    "Tipo da Folha": "Folha Mensal",
    "Nome": "Jaqueline Teodoro Batista",
    "Cargo": "Agente de Combate as Endemias",
    "Vínculo Empregatício": "CONTRATADO",
    "Salário Base": 3242.0,
    "Proventos": 4610.4,
    "Vantagens": 0,
    "Vencimentos Totais": 4610.4,
    "Descontos": 360.45,
    "Líquido": 4249.95
  },
  {
    "Matrícula": "00326410 / 1",
    "Tipo da Folha": "Folha Mensal",
    "Nome": "Joao Gabriel de Jesus Lourenco Souto",
    "Cargo": "Agente de Combate as Endemias",
    "Vínculo Empregatício": "CONTRATADO",
    "Salário Base": 3242.0,
    "Proventos": 4610.4,
    "Vantagens": 0,
    "Vencimentos Totais": 4610.4,
    "Descontos": 355.43,
    "Líquido": 4254.97
  },
  {
    "Matrícula": "00321141 / 1",
    "Tipo da Folha": "Folha Mensal",
    "Nome": "Joao Luiz de Souza Freitas",
    "Cargo": "Agente de Combate as Endemias",
    "Vínculo Empregatício": "CONTRATADO",
    "Salário Base": 3242.0,
    "Proventos": 4592.4,
    "Vantagens": 0,
    "Vencimentos Totais": 4592.4,
    "Descontos": 360.84,
    "Líquido": 4231.56
  },
  {
    "Matrícula": "00326895 / 1",
    "Tipo da Folha": "Folha Mensal",
    "Nome": "Joelma Bonfim Goncalves",
    "Cargo": "Entrevistador Social",
    "Vínculo Empregatício": "CONTRATADO",
    "Salário Base": 1621.0,
    "Proventos": 1566.97,
    "Vantagens": 0,
    "Vencimentos Totais": 1566.97,
    "Descontos": 117.52,
    "Líquido": 1449.45
  },
  {
    "Matrícula": "00321176 / 1",
    "Tipo da Folha": "Folha Mensal",
    "Nome": "Jose Claudio da Silva",
    "Cargo": "Agente de Combate as Endemias",
    "Vínculo Empregatício": "CONTRATADO",
    "Salário Base": 3242.0,
    "Proventos": 4610.4,
    "Vantagens": 0,
    "Vencimentos Totais": 4610.4,
    "Descontos": 355.43,
    "Líquido": 4254.97
  },
  {
    "Matrícula": "00321230 / 1",
    "Tipo da Folha": "Folha Mensal",
    "Nome": "Josimara de Oliveira Martins",
    "Cargo": "Agente de Combate as Endemias",
    "Vínculo Empregatício": "CONTRATADO",
    "Salário Base": 3242.0,
    "Proventos": 4257.36,
    "Vantagens": 0,
    "Vencimentos Totais": 4257.36,
    "Descontos": 308.75,
    "Líquido": 3948.61
  },
  {
    "Matrícula": "00317195 / 1",
    "Tipo da Folha": "Folha Mensal",
    "Nome": "Josimaria de Oliveira Azeredo de Souza",
    "Cargo": "Agente Administrativo",
    "Vínculo Empregatício": "CONTRATADO",
    "Salário Base": 1902.84,
    "Proventos": 2550.84,
    "Vantagens": 0,
    "Vencimentos Totais": 2550.84,
    "Descontos": 167.01,
    "Líquido": 2383.83
  },
  {
    "Matrícula": "00322903 / 1",
    "Tipo da Folha": "Folha Mensal",
    "Nome": "Juliana Alves Pedro",
    "Cargo": "Agente de Combate as Endemias",
    "Vínculo Empregatício": "CONTRATADO",
    "Salário Base": 3242.0,
    "Proventos": 4534.79,
    "Vantagens": 0,
    "Vencimentos Totais": 4534.79,
    "Descontos": 468.01,
    "Líquido": 4066.78
  },
  {
    "Matrícula": "00317225 / 1",
    "Tipo da Folha": "Folha Mensal",
    "Nome": "Juliana da Costa Matos",
    "Cargo": "Agente Administrativo",
    "Vínculo Empregatício": "CONTRATADO",
    "Salário Base": 1902.84,
    "Proventos": 2550.84,
    "Vantagens": 0,
    "Vencimentos Totais": 2550.84,
    "Descontos": 146.93,
    "Líquido": 2403.91
  },
  {
    "Matrícula": "00317209 / 1",
    "Tipo da Folha": "Folha Mensal",
    "Nome": "Juliana de Oliveira Azeredo",
    "Cargo": "Agente Administrativo",
    "Vínculo Empregatício": "CONTRATADO",
    "Salário Base": 1902.84,
    "Proventos": 2550.84,
    "Vantagens": 0,
    "Vencimentos Totais": 2550.84,
    "Descontos": 146.93,
    "Líquido": 2403.91
  },
  {
    "Matrícula": "00322946 / 1",
    "Tipo da Folha": "Folha Mensal",
    "Nome": "Juliana Nogueira da Silva",
    "Cargo": "Agente de Combate as Endemias",
    "Vínculo Empregatício": "CONTRATADO",
    "Salário Base": 3242.0,
    "Proventos": 4610.4,
    "Vantagens": 0,
    "Vencimentos Totais": 4610.4,
    "Descontos": 361.28,
    "Líquido": 4249.12
  },
  {
    "Matrícula": "00326992 / 1",
    "Tipo da Folha": "Folha Mensal",
    "Nome": "Juliana Soares Paula da Silva",
    "Cargo": "Entrevistador Social",
    "Vínculo Empregatício": "CONTRATADO",
    "Salário Base": 1621.0,
    "Proventos": 1632.25,
    "Vantagens": 0,
    "Vencimentos Totais": 1632.25,
    "Descontos": 117.52,
    "Líquido": 1514.73
  },
  {
    "Matrícula": "00321222 / 1",
    "Tipo da Folha": "Folha Mensal",
    "Nome": "Juliana Vieira de Resende",
    "Cargo": "Agente de Combate as Endemias",
    "Vínculo Empregatício": "CONTRATADO",
    "Salário Base": 3242.0,
    "Proventos": 4896.4,
    "Vantagens": 0,
    "Vencimentos Totais": 4896.4,
    "Descontos": 355.43,
    "Líquido": 4540.97
  },
  {
    "Matrícula": "00321214 / 1",
    "Tipo da Folha": "Folha Mensal",
    "Nome": "Julio Rodrigues de Moraes",
    "Cargo": "Agente de Combate as Endemias",
    "Vínculo Empregatício": "CONTRATADO",
    "Salário Base": 3242.0,
    "Proventos": 4628.4,
    "Vantagens": 0,
    "Vencimentos Totais": 4628.4,
    "Descontos": 360.45,
    "Líquido": 4267.95
  },
  {
    "Matrícula": "00321931 / 1",
    "Tipo da Folha": "Folha Mensal",
    "Nome": "Jurema de Carvalho Pinto",
    "Cargo": "Agente de Combate as Endemias",
    "Vínculo Empregatício": "CONTRATADO",
    "Salário Base": 3242.0,
    "Proventos": 1101.39,
    "Vantagens": 0,
    "Vencimentos Totais": 1101.39,
    "Descontos": 1055.27,
    "Líquido": 46.12
  },
  {
    "Matrícula": "00321273 / 1",
    "Tipo da Folha": "Folha Mensal",
    "Nome": "Kamilla Stefany Oliveira da Silva",
    "Cargo": "Agente de Combate as Endemias",
    "Vínculo Empregatício": "CONTRATADO",
    "Salário Base": 3242.0,
    "Proventos": 4610.4,
    "Vantagens": 0,
    "Vencimentos Totais": 4610.4,
    "Descontos": 355.43,
    "Líquido": 4254.97
  },
  {
    "Matrícula": "00318787 / 1",
    "Tipo da Folha": "Rescisão",
    "Nome": "Katia Sena Buarque",
    "Cargo": "Auxiliar de Secretaria Escolar",
    "Vínculo Empregatício": "CONTRATADO",
    "Salário Base": 0.0,
    "Proventos": 855.08,
    "Vantagens": 0,
    "Vencimentos Totais": 855.08,
    "Descontos": 64.16,
    "Líquido": 790.92
  },
  {
    "Matrícula": "00326879 / 1",
    "Tipo da Folha": "Folha Mensal",
    "Nome": "Katia Sena Buarque",
    "Cargo": "Entrevistador Social",
    "Vínculo Empregatício": "CONTRATADO",
    "Salário Base": 1621.0,
    "Proventos": 1566.97,
    "Vantagens": 0,
    "Vencimentos Totais": 1566.97,
    "Descontos": 117.52,
    "Líquido": 1449.45
  },
  {
    "Matrícula": "00321303 / 1",
    "Tipo da Folha": "Folha Mensal",
    "Nome": "Katiana dos Santos da Silva",
    "Cargo": "Agente de Combate as Endemias",
    "Vínculo Empregatício": "CONTRATADO",
    "Salário Base": 3242.0,
    "Proventos": 5063.59,
    "Vantagens": 0,
    "Vencimentos Totais": 5063.59,
    "Descontos": 1225.34,
    "Líquido": 3838.25
  },
  {
    "Matrícula": "00321311 / 1",
    "Tipo da Folha": "Folha Mensal",
    "Nome": "Ketheline do Nascimento Pacheco",
    "Cargo": "Agente de Combate as Endemias",
    "Vínculo Empregatício": "CONTRATADO",
    "Salário Base": 3242.0,
    "Proventos": 4711.6,
    "Vantagens": 0,
    "Vencimentos Totais": 4711.6,
    "Descontos": 367.58,
    "Líquido": 4344.02
  },
  {
    "Matrícula": "00321281 / 1",
    "Tipo da Folha": "Folha Mensal",
    "Nome": "Lediana de Souza Pereira",
    "Cargo": "Agente de Combate as Endemias",
    "Vínculo Empregatício": "CONTRATADO",
    "Salário Base": 3242.0,
    "Proventos": 5063.59,
    "Vantagens": 0,
    "Vencimentos Totais": 5063.59,
    "Descontos": 1361.29,
    "Líquido": 3702.3
  },
  {
    "Matrícula": "00326887 / 1",
    "Tipo da Folha": "Folha Mensal",
    "Nome": "Leonardo Chagas de Alvarenga",
    "Cargo": "Entrevistador Social",
    "Vínculo Empregatício": "CONTRATADO",
    "Salário Base": 1621.0,
    "Proventos": 1566.97,
    "Vantagens": 0,
    "Vencimentos Totais": 1566.97,
    "Descontos": 117.52,
    "Líquido": 1449.45
  },
  {
    "Matrícula": "00320811 / 1",
    "Tipo da Folha": "Rescisão",
    "Nome": "Leonardo Costa Faria",
    "Cargo": "Agente de Combate as Endemias",
    "Vínculo Empregatício": "CONTRATADO",
    "Salário Base": 0.0,
    "Proventos": 6846.14,
    "Vantagens": 0,
    "Vencimentos Totais": 6846.14,
    "Descontos": 2172.45,
    "Líquido": 4673.69
  },
  {
    "Matrícula": "00320803 / 1",
    "Tipo da Folha": "Folha Mensal",
    "Nome": "Levi Muzzi",
    "Cargo": "Agente de Combate as Endemias",
    "Vínculo Empregatício": "CONTRATADO",
    "Salário Base": 3242.0,
    "Proventos": 4610.4,
    "Vantagens": 0,
    "Vencimentos Totais": 4610.4,
    "Descontos": 355.43,
    "Líquido": 4254.97
  },
  {
    "Matrícula": "00326968 / 1",
    "Tipo da Folha": "Folha Mensal",
    "Nome": "Lidiane Costa de Souza",
    "Cargo": "Entrevistador Social",
    "Vínculo Empregatício": "CONTRATADO",
    "Salário Base": 1621.0,
    "Proventos": 1566.97,
    "Vantagens": 0,
    "Vencimentos Totais": 1566.97,
    "Descontos": 117.52,
    "Líquido": 1449.45
  },
  {
    "Matrícula": "00324582 / 1",
    "Tipo da Folha": "Folha Mensal",
    "Nome": "Lidiane de Almeida Santos",
    "Cargo": "Tecnico de Aparelho Gessado",
    "Vínculo Empregatício": "CONTRATADO",
    "Salário Base": 1902.84,
    "Proventos": 2440.26,
    "Vantagens": 0,
    "Vencimentos Totais": 2440.26,
    "Descontos": 204.08,
    "Líquido": 2236.18
  },
  {
    "Matrícula": "00324957 / 1",
    "Tipo da Folha": "Folha Mensal",
    "Nome": "Lidiane Portela da Silva",
    "Cargo": "Agente Administrativo",
    "Vínculo Empregatício": "CONTRATADO",
    "Salário Base": 1902.84,
    "Proventos": 2550.84,
    "Vantagens": 0,
    "Vencimentos Totais": 2550.84,
    "Descontos": 146.93,
    "Líquido": 2403.91
  },
  {
    "Matrícula": "00320790 / 1",
    "Tipo da Folha": "Folha Mensal",
    "Nome": "Lilian Barcelos dos Santos Azeredo",
    "Cargo": "Agente de Combate as Endemias",
    "Vínculo Empregatício": "CONTRATADO",
    "Salário Base": 3242.0,
    "Proventos": 4912.36,
    "Vantagens": 0,
    "Vencimentos Totais": 4912.36,
    "Descontos": 1430.43,
    "Líquido": 3481.93
  },
  {
    "Matrícula": "00318817 / 1",
    "Tipo da Folha": "Folha Mensal",
    "Nome": "Liliane Felix de Almeida",
    "Cargo": "Auxiliar de Secretaria Escolar",
    "Vínculo Empregatício": "CONTRATADO",
    "Salário Base": 1621.0,
    "Proventos": 2341.0,
    "Vantagens": 0,
    "Vencimentos Totais": 2341.0,
    "Descontos": 136.63,
    "Líquido": 2204.37
  },
  {
    "Matrícula": "00322997 / 1",
    "Tipo da Folha": "Folha Mensal",
    "Nome": "Lorena Andrade Silva de Sousa Jorge Bogado",
    "Cargo": "Agente de Combate as Endemias",
    "Vínculo Empregatício": "CONTRATADO",
    "Salário Base": 3242.0,
    "Proventos": 4646.4,
    "Vantagens": 0,
    "Vencimentos Totais": 4646.4,
    "Descontos": 375.51,
    "Líquido": 4270.89
  },
  {
    "Matrícula": "00321320 / 1",
    "Tipo da Folha": "Folha Mensal",
    "Nome": "Lucia Helena da Conceicao Andrade Maciel",
    "Cargo": "Agente de Combate as Endemias",
    "Vínculo Empregatício": "CONTRATADO",
    "Salário Base": 3242.0,
    "Proventos": 4592.4,
    "Vantagens": 0,
    "Vencimentos Totais": 4592.4,
    "Descontos": 355.43,
    "Líquido": 4236.97
  },
  {
    "Matrícula": "00321338 / 1",
    "Tipo da Folha": "Folha Mensal",
    "Nome": "Luciana Gomes Carvalhaes",
    "Cargo": "Agente de Combate as Endemias",
    "Vínculo Empregatício": "CONTRATADO",
    "Salário Base": 3242.0,
    "Proventos": 4592.4,
    "Vantagens": 0,
    "Vencimentos Totais": 4592.4,
    "Descontos": 355.43,
    "Líquido": 4236.97
  },
  {
    "Matrícula": "00321346 / 1",
    "Tipo da Folha": "Folha Mensal",
    "Nome": "Luciene Albernaz Barao Soares",
    "Cargo": "Agente de Combate as Endemias",
    "Vínculo Empregatício": "CONTRATADO",
    "Salário Base": 3242.0,
    "Proventos": 4646.4,
    "Vantagens": 0,
    "Vencimentos Totais": 4646.4,
    "Descontos": 355.43,
    "Líquido": 4290.97
  },
  {
    "Matrícula": "00320773 / 1",
    "Tipo da Folha": "Folha Mensal",
    "Nome": "Luise Helena Queiroz Hortencio",
    "Cargo": "Agente de Combate as Endemias",
    "Vínculo Empregatício": "CONTRATADO",
    "Salário Base": 3242.0,
    "Proventos": 5027.59,
    "Vantagens": 0,
    "Vencimentos Totais": 5027.59,
    "Descontos": 1735.81,
    "Líquido": 3291.78
  },
  {
    "Matrícula": "00319228 / 1",
    "Tipo da Folha": "Folha Mensal",
    "Nome": "Luiz Henrique Vieira Matos",
    "Cargo": "Agente Administrativo",
    "Vínculo Empregatício": "CONTRATADO",
    "Salário Base": 1902.84,
    "Proventos": 2622.84,
    "Vantagens": 0,
    "Vencimentos Totais": 2622.84,
    "Descontos": 146.93,
    "Líquido": 2475.91
  },
  {
    "Matrícula": "00318671 / 1",
    "Tipo da Folha": "Folha Mensal",
    "Nome": "Luiz Ricardo Pereira Gonçalves",
    "Cargo": "Agente Administrativo",
    "Vínculo Empregatício": "CONTRATADO",
    "Salário Base": 1902.84,
    "Proventos": 2658.84,
    "Vantagens": 0,
    "Vencimentos Totais": 2658.84,
    "Descontos": 146.93,
    "Líquido": 2511.91
  },
  {
    "Matrícula": "00324930 / 1",
    "Tipo da Folha": "Folha Mensal",
    "Nome": "Marcela Elias da Silva",
    "Cargo": "Agente Administrativo",
    "Vínculo Empregatício": "CONTRATADO",
    "Salário Base": 1902.84,
    "Proventos": 2553.38,
    "Vantagens": 0,
    "Vencimentos Totais": 2553.38,
    "Descontos": 146.93,
    "Líquido": 2406.45
  },
  {
    "Matrícula": "00323454 / 1",
    "Tipo da Folha": "Folha Mensal",
    "Nome": "Marcelo de Carvalho Marinho",
    "Cargo": "Motorista",
    "Vínculo Empregatício": "CONTRATADO",
    "Salário Base": 1621.0,
    "Proventos": 4677.71,
    "Vantagens": 0,
    "Vencimentos Totais": 4677.71,
    "Descontos": 230.99,
    "Líquido": 4446.72
  },
  {
    "Matrícula": "00320757 / 1",
    "Tipo da Folha": "Folha Mensal",
    "Nome": "Marcelo Goncalves da Silva",
    "Cargo": "Agente de Combate as Endemias",
    "Vínculo Empregatício": "CONTRATADO",
    "Salário Base": 3242.0,
    "Proventos": 4646.4,
    "Vantagens": 0,
    "Vencimentos Totais": 4646.4,
    "Descontos": 355.43,
    "Líquido": 4290.97
  },
  {
    "Matrícula": "00321079 / 1",
    "Tipo da Folha": "Folha Mensal",
    "Nome": "Marcelo Guilherme do Espirito Santo",
    "Cargo": "Agente de Combate as Endemias",
    "Vínculo Empregatício": "CONTRATADO",
    "Salário Base": 3242.0,
    "Proventos": 4610.4,
    "Vantagens": 0,
    "Vencimentos Totais": 4610.4,
    "Descontos": 355.43,
    "Líquido": 4254.97
  },
  {
    "Matrícula": "00318809 / 1",
    "Tipo da Folha": "Folha Mensal",
    "Nome": "Marcia Brito de Lima de Oliveira",
    "Cargo": "Auxiliar de Secretaria Escolar",
    "Vínculo Empregatício": "CONTRATADO",
    "Salário Base": 1621.0,
    "Proventos": 2341.0,
    "Vantagens": 0,
    "Vencimentos Totais": 2341.0,
    "Descontos": 121.57,
    "Líquido": 2219.43
  },
  {
    "Matrícula": "00321044 / 1",
    "Tipo da Folha": "Folha Mensal",
    "Nome": "Marcia Meri de Lima Risso Guedes",
    "Cargo": "Agente de Combate as Endemias",
    "Vínculo Empregatício": "CONTRATADO",
    "Salário Base": 3242.0,
    "Proventos": 4610.4,
    "Vantagens": 0,
    "Vencimentos Totais": 4610.4,
    "Descontos": 355.43,
    "Líquido": 4254.97
  },
  {
    "Matrícula": "00321060 / 1",
    "Tipo da Folha": "Folha Mensal",
    "Nome": "Marcia Valeria Oliveira Machado",
    "Cargo": "Agente de Combate as Endemias",
    "Vínculo Empregatício": "CONTRATADO",
    "Salário Base": 3242.0,
    "Proventos": 4610.4,
    "Vantagens": 0,
    "Vencimentos Totais": 4610.4,
    "Descontos": 355.43,
    "Líquido": 4254.97
  },
  {
    "Matrícula": "00321052 / 1",
    "Tipo da Folha": "Folha Mensal",
    "Nome": "Marcio Martins Moreira",
    "Cargo": "Agente de Combate as Endemias",
    "Vínculo Empregatício": "CONTRATADO",
    "Salário Base": 3242.0,
    "Proventos": 4430.4,
    "Vantagens": 0,
    "Vencimentos Totais": 4430.4,
    "Descontos": 365.47,
    "Líquido": 4064.93
  },
  {
    "Matrícula": "00321028 / 1",
    "Tipo da Folha": "Folha Mensal",
    "Nome": "Marco Antonio Alves Nogueira",
    "Cargo": "Agente de Combate as Endemias",
    "Vínculo Empregatício": "CONTRATADO",
    "Salário Base": 3242.0,
    "Proventos": 4646.4,
    "Vantagens": 0,
    "Vencimentos Totais": 4646.4,
    "Descontos": 385.55,
    "Líquido": 4260.85
  },
  {
    "Matrícula": "00322970 / 1",
    "Tipo da Folha": "Folha Mensal",
    "Nome": "Marcos Paulo Costa Lima",
    "Cargo": "Agente de Combate as Endemias",
    "Vínculo Empregatício": "CONTRATADO",
    "Salário Base": 3242.0,
    "Proventos": 4610.4,
    "Vantagens": 0,
    "Vencimentos Totais": 4610.4,
    "Descontos": 355.43,
    "Líquido": 4254.97
  },
  {
    "Matrícula": "00321036 / 1",
    "Tipo da Folha": "Folha Mensal",
    "Nome": "Maria Cristina Coelho Teixeira",
    "Cargo": "Agente de Combate as Endemias",
    "Vínculo Empregatício": "CONTRATADO",
    "Salário Base": 3242.0,
    "Proventos": 4610.4,
    "Vantagens": 0,
    "Vencimentos Totais": 4610.4,
    "Descontos": 355.43,
    "Líquido": 4254.97
  },
  {
    "Matrícula": "00321010 / 1",
    "Tipo da Folha": "Folha Mensal",
    "Nome": "Maria de Fatima de Souza Duarte",
    "Cargo": "Agente de Combate as Endemias",
    "Vínculo Empregatício": "CONTRATADO",
    "Salário Base": 3242.0,
    "Proventos": 4646.4,
    "Vantagens": 0,
    "Vencimentos Totais": 4646.4,
    "Descontos": 355.43,
    "Líquido": 4290.97
  },
  {
    "Matrícula": "00327077 / 1",
    "Tipo da Folha": "Folha Complementar (02/2026)",
    "Nome": "Maria Eduarda Gomes Chaves",
    "Cargo": "Entrevistador Social",
    "Vínculo Empregatício": "CONTRATADO",
    "Salário Base": 0.0,
    "Proventos": 432.26,
    "Vantagens": 0,
    "Vencimentos Totais": 432.26,
    "Descontos": 32.41,
    "Líquido": 399.85
  },
  {
    "Matrícula": "00319252 / 1",
    "Tipo da Folha": "Folha Mensal",
    "Nome": "Maria Ivone Lima da Cunha Dal Bello",
    "Cargo": "Auxiliar de Secretaria Escolar",
    "Vínculo Empregatício": "CONTRATADO",
    "Salário Base": 1621.0,
    "Proventos": 2269.0,
    "Vantagens": 0,
    "Vencimentos Totais": 2269.0,
    "Descontos": 201.54,
    "Líquido": 2067.46
  },
  {
    "Matrícula": "00324590 / 1",
    "Tipo da Folha": "Folha Mensal",
    "Nome": "Maria Sonia Menario",
    "Cargo": "Tecnico de Aparelho Gessado",
    "Vínculo Empregatício": "CONTRATADO",
    "Salário Base": 1902.84,
    "Proventos": 2538.91,
    "Vantagens": 0,
    "Vencimentos Totais": 2538.91,
    "Descontos": 191.22,
    "Líquido": 2347.69
  },
  {
    "Matrícula": "00323152 / 1",
    "Tipo da Folha": "Folha Mensal",
    "Nome": "Marianna Erasmo da Silva",
    "Cargo": "Agente de Combate as Endemias",
    "Vínculo Empregatício": "CONTRATADO",
    "Salário Base": 3242.0,
    "Proventos": 4610.4,
    "Vantagens": 0,
    "Vencimentos Totais": 4610.4,
    "Descontos": 355.43,
    "Líquido": 4254.97
  },
  {
    "Matrícula": "00323012 / 1",
    "Tipo da Folha": "Folha Mensal",
    "Nome": "Marilea da Silva Barbosa",
    "Cargo": "Agente Administrativo",
    "Vínculo Empregatício": "CONTRATADO",
    "Salário Base": 1902.84,
    "Proventos": 2622.84,
    "Vantagens": 0,
    "Vencimentos Totais": 2622.84,
    "Descontos": 146.93,
    "Líquido": 2475.91
  },
  {
    "Matrícula": "00321672 / 1",
    "Tipo da Folha": "Folha Mensal",
    "Nome": "Marli Martins Nunes",
    "Cargo": "Agente de Combate as Endemias",
    "Vínculo Empregatício": "CONTRATADO",
    "Salário Base": 3242.0,
    "Proventos": 4610.4,
    "Vantagens": 0,
    "Vencimentos Totais": 4610.4,
    "Descontos": 355.43,
    "Líquido": 4254.97
  },
  {
    "Matrícula": "00326933 / 1",
    "Tipo da Folha": "Folha Mensal",
    "Nome": "Mayra Gomes da Silva",
    "Cargo": "Entrevistador Social",
    "Vínculo Empregatício": "CONTRATADO",
    "Salário Base": 1621.0,
    "Proventos": 1953.46,
    "Vantagens": 0,
    "Vencimentos Totais": 1953.46,
    "Descontos": 117.52,
    "Líquido": 1835.94
  },
  {
    "Matrícula": "00321761 / 1",
    "Tipo da Folha": "Folha Mensal",
    "Nome": "Michele Fernanda Santos",
    "Cargo": "Agente de Combate as Endemias",
    "Vínculo Empregatício": "CONTRATADO",
    "Salário Base": 3242.0,
    "Proventos": 4646.4,
    "Vantagens": 0,
    "Vencimentos Totais": 4646.4,
    "Descontos": 355.43,
    "Líquido": 4290.97
  },
  {
    "Matrícula": "00323187 / 1",
    "Tipo da Folha": "Folha Mensal",
    "Nome": "Miguel Rocha de Lima Risso Guedes",
    "Cargo": "Agente de Combate as Endemias",
    "Vínculo Empregatício": "CONTRATADO",
    "Salário Base": 3242.0,
    "Proventos": 4610.4,
    "Vantagens": 0,
    "Vencimentos Totais": 4610.4,
    "Descontos": 355.43,
    "Líquido": 4254.97
  },
  {
    "Matrícula": "00321753 / 1",
    "Tipo da Folha": "Folha Mensal",
    "Nome": "Monica Martins Mendes Guedes",
    "Cargo": "Agente de Combate as Endemias",
    "Vínculo Empregatício": "CONTRATADO",
    "Salário Base": 3242.0,
    "Proventos": 5063.59,
    "Vantagens": 0,
    "Vencimentos Totais": 5063.59,
    "Descontos": 1214.48,
    "Líquido": 3849.11
  },
  {
    "Matrícula": "00322814 / 1",
    "Tipo da Folha": "Folha Mensal",
    "Nome": "Monika da Silva Maia",
    "Cargo": "Agente Administrativo",
    "Vínculo Empregatício": "CONTRATADO",
    "Salário Base": 1902.84,
    "Proventos": 2622.84,
    "Vantagens": 0,
    "Vencimentos Totais": 2622.84,
    "Descontos": 146.93,
    "Líquido": 2475.91
  },
  {
    "Matrícula": "00324655 / 1",
    "Tipo da Folha": "Folha Mensal",
    "Nome": "Natalia de Souza Reis",
    "Cargo": "Agente Administrativo",
    "Vínculo Empregatício": "CONTRATADO",
    "Salário Base": 1902.84,
    "Proventos": 2060.83,
    "Vantagens": 0,
    "Vencimentos Totais": 2060.83,
    "Descontos": 85.62,
    "Líquido": 1975.21
  },
  {
    "Matrícula": "00321770 / 1",
    "Tipo da Folha": "Folha Mensal",
    "Nome": "Neilton Jose dos Santos",
    "Cargo": "Agente de Combate as Endemias",
    "Vínculo Empregatício": "CONTRATADO",
    "Salário Base": 3242.0,
    "Proventos": 4610.4,
    "Vantagens": 0,
    "Vencimentos Totais": 4610.4,
    "Descontos": 355.43,
    "Líquido": 4254.97
  },
  {
    "Matrícula": "00326984 / 1",
    "Tipo da Folha": "Folha Mensal",
    "Nome": "Neuci Rocha Aguiar",
    "Cargo": "Entrevistador Social",
    "Vínculo Empregatício": "CONTRATADO",
    "Salário Base": 1621.0,
    "Proventos": 1566.97,
    "Vantagens": 0,
    "Vencimentos Totais": 1566.97,
    "Descontos": 117.52,
    "Líquido": 1449.45
  },
  {
    "Matrícula": "00321699 / 1",
    "Tipo da Folha": "Folha Mensal",
    "Nome": "Orlando da Silva Couto",
    "Cargo": "Agente de Combate as Endemias",
    "Vínculo Empregatício": "CONTRATADO",
    "Salário Base": 3242.0,
    "Proventos": 4610.4,
    "Vantagens": 0,
    "Vencimentos Totais": 4610.4,
    "Descontos": 355.43,
    "Líquido": 4254.97
  },
  {
    "Matrícula": "00321680 / 1",
    "Tipo da Folha": "Folha Mensal",
    "Nome": "Osvaldo Walmor Torres Ojeda Junior",
    "Cargo": "Agente de Combate as Endemias",
    "Vínculo Empregatício": "CONTRATADO",
    "Salário Base": 3242.0,
    "Proventos": 4646.4,
    "Vantagens": 0,
    "Vencimentos Totais": 4646.4,
    "Descontos": 380.53,
    "Líquido": 4265.87
  },
  {
    "Matrícula": "00321702 / 1",
    "Tipo da Folha": "Folha Mensal",
    "Nome": "Paula Beatriz Bitencourt Tavares Duarte",
    "Cargo": "Agente de Combate as Endemias",
    "Vínculo Empregatício": "CONTRATADO",
    "Salário Base": 3242.0,
    "Proventos": 4552.79,
    "Vantagens": 0,
    "Vencimentos Totais": 4552.79,
    "Descontos": 497.28,
    "Líquido": 4055.51
  },
  {
    "Matrícula": "00321710 / 1",
    "Tipo da Folha": "Folha Mensal",
    "Nome": "Paula Freitas de Sousa",
    "Cargo": "Agente de Combate as Endemias",
    "Vínculo Empregatício": "CONTRATADO",
    "Salário Base": 3242.0,
    "Proventos": 4610.4,
    "Vantagens": 0,
    "Vencimentos Totais": 4610.4,
    "Descontos": 355.43,
    "Líquido": 4254.97
  },
  {
    "Matrícula": "00321729 / 1",
    "Tipo da Folha": "Folha Mensal",
    "Nome": "Pedro Luiz Perdigao",
    "Cargo": "Agente de Combate as Endemias",
    "Vínculo Empregatício": "CONTRATADO",
    "Salário Base": 3242.0,
    "Proventos": 6929.33,
    "Vantagens": 0,
    "Vencimentos Totais": 6929.33,
    "Descontos": 869.0,
    "Líquido": 6060.33
  },
  {
    "Matrícula": "00325945 / 1",
    "Tipo da Folha": "Folha Mensal",
    "Nome": "Priscilla da Silva Vieira",
    "Cargo": "Agente Administrativo",
    "Vínculo Empregatício": "CONTRATADO",
    "Salário Base": 1902.84,
    "Proventos": 2692.92,
    "Vantagens": 0,
    "Vencimentos Totais": 2692.92,
    "Descontos": 156.97,
    "Líquido": 2535.95
  },
  {
    "Matrícula": "00323772 / 1",
    "Tipo da Folha": "Folha Mensal",
    "Nome": "Rafael de Souza Almeida",
    "Cargo": "Motorista",
    "Vínculo Empregatício": "CONTRATADO",
    "Salário Base": 1621.0,
    "Proventos": 2411.08,
    "Vantagens": 0,
    "Vencimentos Totais": 2411.08,
    "Descontos": 121.57,
    "Líquido": 2289.51
  },
  {
    "Matrícula": "00326550 / 1",
    "Tipo da Folha": "Folha Mensal",
    "Nome": "Ramon Rial Pelacani",
    "Cargo": "Engenheiro do Trabalho",
    "Vínculo Empregatício": "CONTRATADO",
    "Salário Base": 10514.51,
    "Proventos": 11558.71,
    "Vantagens": 0,
    "Vencimentos Totais": 11558.71,
    "Descontos": 2741.14,
    "Líquido": 8817.57
  },
  {
    "Matrícula": "00324973 / 1",
    "Tipo da Folha": "Folha Mensal",
    "Nome": "Rejane Andrea Ventapane dos Reis",
    "Cargo": "Agente Administrativo",
    "Vínculo Empregatício": "CONTRATADO",
    "Salário Base": 1902.84,
    "Proventos": 2658.84,
    "Vantagens": 0,
    "Vencimentos Totais": 2658.84,
    "Descontos": 156.97,
    "Líquido": 2501.87
  },
  {
    "Matrícula": "00322091 / 1",
    "Tipo da Folha": "Folha Mensal",
    "Nome": "Rejane da Silva Goncalves Faria",
    "Cargo": "Agente de Combate as Endemias",
    "Vínculo Empregatício": "CONTRATADO",
    "Salário Base": 3242.0,
    "Proventos": 4646.4,
    "Vantagens": 0,
    "Vencimentos Totais": 4646.4,
    "Descontos": 355.43,
    "Líquido": 4290.97
  },
  {
    "Matrícula": "00324981 / 1",
    "Tipo da Folha": "Folha Mensal",
    "Nome": "Rejane Morais da Gama Wollmann",
    "Cargo": "Agente Administrativo",
    "Vínculo Empregatício": "CONTRATADO",
    "Salário Base": 1902.84,
    "Proventos": 2658.84,
    "Vantagens": 0,
    "Vencimentos Totais": 2658.84,
    "Descontos": 146.93,
    "Líquido": 2511.91
  },
  {
    "Matrícula": "00321745 / 1",
    "Tipo da Folha": "Folha Mensal",
    "Nome": "Renata de Santana Levino",
    "Cargo": "Agente de Combate as Endemias",
    "Vínculo Empregatício": "CONTRATADO",
    "Salário Base": 3242.0,
    "Proventos": 4646.4,
    "Vantagens": 0,
    "Vencimentos Totais": 4646.4,
    "Descontos": 360.45,
    "Líquido": 4285.95
  },
  {
    "Matrícula": "00323764 / 1",
    "Tipo da Folha": "Folha Mensal",
    "Nome": "Renato Pinto Gouvea",
    "Cargo": "Motorista",
    "Vínculo Empregatício": "CONTRATADO",
    "Salário Base": 1621.0,
    "Proventos": 4162.25,
    "Vantagens": 0,
    "Vencimentos Totais": 4162.25,
    "Descontos": 210.16,
    "Líquido": 3952.09
  },
  {
    "Matrícula": "00321826 / 1",
    "Tipo da Folha": "Folha Mensal",
    "Nome": "Rildo de Souza Azevedo",
    "Cargo": "Agente de Combate as Endemias",
    "Vínculo Empregatício": "CONTRATADO",
    "Salário Base": 3242.0,
    "Proventos": 4646.4,
    "Vantagens": 0,
    "Vencimentos Totais": 4646.4,
    "Descontos": 360.45,
    "Líquido": 4285.95
  },
  {
    "Matrícula": "00321834 / 1",
    "Tipo da Folha": "Folha Mensal",
    "Nome": "Roberto Garcia Bersot",
    "Cargo": "Agente de Combate as Endemias",
    "Vínculo Empregatício": "CONTRATADO",
    "Salário Base": 3242.0,
    "Proventos": 4646.4,
    "Vantagens": 0,
    "Vencimentos Totais": 4646.4,
    "Descontos": 355.43,
    "Líquido": 4290.97
  },
  {
    "Matrícula": "00323608 / 1",
    "Tipo da Folha": "Folha Mensal",
    "Nome": "Rogerio de Souza Amaro",
    "Cargo": "Motorista",
    "Vínculo Empregatício": "CONTRATADO",
    "Salário Base": 1621.0,
    "Proventos": 2341.0,
    "Vantagens": 0,
    "Vencimentos Totais": 2341.0,
    "Descontos": 121.57,
    "Líquido": 2219.43
  },
  {
    "Matrícula": "00321842 / 1",
    "Tipo da Folha": "Folha Mensal",
    "Nome": "Ronaldo Dutra da Silva",
    "Cargo": "Agente de Combate as Endemias",
    "Vínculo Empregatício": "CONTRATADO",
    "Salário Base": 3242.0,
    "Proventos": 4646.4,
    "Vantagens": 0,
    "Vencimentos Totais": 4646.4,
    "Descontos": 355.43,
    "Líquido": 4290.97
  },
  {
    "Matrícula": "00324612 / 1",
    "Tipo da Folha": "Folha Mensal",
    "Nome": "Rosa Maria Monteiro Rodrigues Rangel",
    "Cargo": "Agente Administrativo",
    "Vínculo Empregatício": "CONTRATADO",
    "Salário Base": 1902.84,
    "Proventos": 2968.03,
    "Vantagens": 0,
    "Vencimentos Totais": 2968.03,
    "Descontos": 146.93,
    "Líquido": 2821.1
  },
  {
    "Matrícula": "00321850 / 1",
    "Tipo da Folha": "Folha Mensal",
    "Nome": "Rosana Cavalcanti da Silva",
    "Cargo": "Agente de Combate as Endemias",
    "Vínculo Empregatício": "CONTRATADO",
    "Salário Base": 3242.0,
    "Proventos": 4646.4,
    "Vantagens": 0,
    "Vencimentos Totais": 4646.4,
    "Descontos": 434.06,
    "Líquido": 4212.34
  },
  {
    "Matrícula": "00326976 / 1",
    "Tipo da Folha": "Folha Mensal",
    "Nome": "Rosinete Bispo Nascimento Ramos Rodrigues Costa",
    "Cargo": "Entrevistador Social",
    "Vínculo Empregatício": "CONTRATADO",
    "Salário Base": 1621.0,
    "Proventos": 1566.97,
    "Vantagens": 0,
    "Vencimentos Totais": 1566.97,
    "Descontos": 117.52,
    "Líquido": 1449.45
  },
  {
    "Matrícula": "00321869 / 1",
    "Tipo da Folha": "Folha Mensal",
    "Nome": "Rutileia Scarpatti Cabral",
    "Cargo": "Agente de Combate as Endemias",
    "Vínculo Empregatício": "CONTRATADO",
    "Salário Base": 3242.0,
    "Proventos": 4588.79,
    "Vantagens": 0,
    "Vencimentos Totais": 4588.79,
    "Descontos": 447.93,
    "Líquido": 4140.86
  },
  {
    "Matrícula": "00326275 / 1",
    "Tipo da Folha": "Folha Mensal",
    "Nome": "Sabrina da Silva Rangel",
    "Cargo": "Motorista",
    "Vínculo Empregatício": "CONTRATADO",
    "Salário Base": 1621.0,
    "Proventos": 2810.27,
    "Vantagens": 0,
    "Vencimentos Totais": 2810.27,
    "Descontos": 1058.68,
    "Líquido": 1751.59
  },
  {
    "Matrícula": "00316598 / 2",
    "Tipo da Folha": "Folha Mensal",
    "Nome": "Sara Ferreira",
    "Cargo": "Agente Administrativo",
    "Vínculo Empregatício": "CONTRATADO",
    "Salário Base": 1902.84,
    "Proventos": 2620.92,
    "Vantagens": 0,
    "Vencimentos Totais": 2620.92,
    "Descontos": 167.01,
    "Líquido": 2453.91
  },
  {
    "Matrícula": "00322083 / 1",
    "Tipo da Folha": "Folha Mensal",
    "Nome": "Sergio Roberto Pereira Braga",
    "Cargo": "Agente de Combate as Endemias",
    "Vínculo Empregatício": "CONTRATADO",
    "Salário Base": 3242.0,
    "Proventos": 4628.4,
    "Vantagens": 0,
    "Vencimentos Totais": 4628.4,
    "Descontos": 355.43,
    "Líquido": 4272.97
  },
  {
    "Matrícula": "00317217 / 1",
    "Tipo da Folha": "Folha Mensal",
    "Nome": "Sheila Rosa Hermogenio Moreira",
    "Cargo": "Agente Administrativo",
    "Vínculo Empregatício": "CONTRATADO",
    "Salário Base": 1902.84,
    "Proventos": 3076.03,
    "Vantagens": 0,
    "Vencimentos Totais": 3076.03,
    "Descontos": 1162.83,
    "Líquido": 1913.2
  },
  {
    "Matrícula": "00320684 / 1",
    "Tipo da Folha": "Folha Mensal",
    "Nome": "Silvio Nogueira de Oliveira",
    "Cargo": "Agente Administrativo",
    "Vínculo Empregatício": "CONTRATADO",
    "Salário Base": 1902.84,
    "Proventos": 2586.84,
    "Vantagens": 0,
    "Vencimentos Totais": 2586.84,
    "Descontos": 151.95,
    "Líquido": 2434.89
  },
  {
    "Matrícula": "00327000 / 1",
    "Tipo da Folha": "Folha Mensal",
    "Nome": "Simara Rocha Mattos da Silva",
    "Cargo": "Entrevistador Social",
    "Vínculo Empregatício": "CONTRATADO",
    "Salário Base": 1621.0,
    "Proventos": 1566.97,
    "Vantagens": 0,
    "Vencimentos Totais": 1566.97,
    "Descontos": 117.52,
    "Líquido": 1449.45
  },
  {
    "Matrícula": "00319961 / 1",
    "Tipo da Folha": "Folha Mensal",
    "Nome": "Simone de Barros Preza",
    "Cargo": "Agente Administrativo",
    "Vínculo Empregatício": "CONTRATADO",
    "Salário Base": 1902.84,
    "Proventos": 2582.38,
    "Vantagens": 0,
    "Vencimentos Totais": 2582.38,
    "Descontos": 225.56,
    "Líquido": 2356.82
  },
  {
    "Matrícula": "00321966 / 1",
    "Tipo da Folha": "Folha Mensal",
    "Nome": "Simone Viana",
    "Cargo": "Agente de Combate as Endemias",
    "Vínculo Empregatício": "CONTRATADO",
    "Salário Base": 3242.0,
    "Proventos": 3242.0,
    "Vantagens": 0,
    "Vencimentos Totais": 3242.0,
    "Descontos": 3242.0,
    "Líquido": 0.0
  },
  {
    "Matrícula": "00322059 / 1",
    "Tipo da Folha": "Folha Mensal",
    "Nome": "Soraia Orsi dos Santos",
    "Cargo": "Agente de Combate as Endemias",
    "Vínculo Empregatício": "CONTRATADO",
    "Salário Base": 3242.0,
    "Proventos": 4646.4,
    "Vantagens": 0,
    "Vencimentos Totais": 4646.4,
    "Descontos": 355.43,
    "Líquido": 4290.97
  },
  {
    "Matrícula": "00322075 / 1",
    "Tipo da Folha": "Folha Mensal",
    "Nome": "Sueli Peres da Silva",
    "Cargo": "Agente de Combate as Endemias",
    "Vínculo Empregatício": "CONTRATADO",
    "Salário Base": 3242.0,
    "Proventos": 4646.4,
    "Vantagens": 0,
    "Vencimentos Totais": 4646.4,
    "Descontos": 355.43,
    "Líquido": 4290.97
  },
  {
    "Matrícula": "00322067 / 1",
    "Tipo da Folha": "Folha Mensal",
    "Nome": "Taciana Lirio Ramos Freire",
    "Cargo": "Agente de Combate as Endemias",
    "Vínculo Empregatício": "CONTRATADO",
    "Salário Base": 3242.0,
    "Proventos": 4646.4,
    "Vantagens": 0,
    "Vencimentos Totais": 4646.4,
    "Descontos": 355.43,
    "Líquido": 4290.97
  },
  {
    "Matrícula": "00322032 / 1",
    "Tipo da Folha": "Folha Mensal",
    "Nome": "Tania Mara Silva Garcia Villela",
    "Cargo": "Agente de Combate as Endemias",
    "Vínculo Empregatício": "CONTRATADO",
    "Salário Base": 3242.0,
    "Proventos": 4610.4,
    "Vantagens": 0,
    "Vencimentos Totais": 4610.4,
    "Descontos": 355.43,
    "Líquido": 4254.97
  },
  {
    "Matrícula": "00322040 / 1",
    "Tipo da Folha": "Folha Mensal",
    "Nome": "Tatiana de Souza Madeira",
    "Cargo": "Agente de Combate as Endemias",
    "Vínculo Empregatício": "CONTRATADO",
    "Salário Base": 3242.0,
    "Proventos": 4646.4,
    "Vantagens": 0,
    "Vencimentos Totais": 4646.4,
    "Descontos": 406.5,
    "Líquido": 4239.9
  },
  {
    "Matrícula": "00327093 / 1",
    "Tipo da Folha": "Folha Complementar (02/2026)",
    "Nome": "Tatiana Gomes Ferreira Pereira",
    "Cargo": "Entrevistador Social",
    "Vínculo Empregatício": "CONTRATADO",
    "Salário Base": 0.0,
    "Proventos": 432.26,
    "Vantagens": 0,
    "Vencimentos Totais": 432.26,
    "Descontos": 32.41,
    "Líquido": 399.85
  },
  {
    "Matrícula": "00322024 / 1",
    "Tipo da Folha": "Folha Mensal",
    "Nome": "Tatiane de Souza Dias Urias",
    "Cargo": "Agente de Combate as Endemias",
    "Vínculo Empregatício": "CONTRATADO",
    "Salário Base": 3242.0,
    "Proventos": 4610.4,
    "Vantagens": 0,
    "Vencimentos Totais": 4610.4,
    "Descontos": 355.43,
    "Líquido": 4254.97
  },
  {
    "Matrícula": "00322008 / 1",
    "Tipo da Folha": "Folha Mensal",
    "Nome": "Tayna da Silva Heggdorne",
    "Cargo": "Agente de Combate as Endemias",
    "Vínculo Empregatício": "CONTRATADO",
    "Salário Base": 3242.0,
    "Proventos": 4973.59,
    "Vantagens": 0,
    "Vencimentos Totais": 4973.59,
    "Descontos": 1189.38,
    "Líquido": 3784.21
  },
  {
    "Matrícula": "00322016 / 1",
    "Tipo da Folha": "Folha Mensal",
    "Nome": "Telma Jorge Bogado",
    "Cargo": "Agente de Combate as Endemias",
    "Vínculo Empregatício": "CONTRATADO",
    "Salário Base": 3242.0,
    "Proventos": 5063.59,
    "Vantagens": 0,
    "Vencimentos Totais": 5063.59,
    "Descontos": 360.45,
    "Líquido": 4703.14
  },
  {
    "Matrícula": "00318833 / 1",
    "Tipo da Folha": "Folha Mensal",
    "Nome": "Telma June Fernandes da Silva",
    "Cargo": "Auxiliar de Secretaria Escolar",
    "Vínculo Empregatício": "CONTRATADO",
    "Salário Base": 1621.0,
    "Proventos": 2375.08,
    "Vantagens": 0,
    "Vencimentos Totais": 2375.08,
    "Descontos": 131.61,
    "Líquido": 2243.47
  },
  {
    "Matrícula": "00323195 / 1",
    "Tipo da Folha": "Folha Mensal",
    "Nome": "Thawan Gonzalez Araujo Silva",
    "Cargo": "Agente de Combate as Endemias",
    "Vínculo Empregatício": "CONTRATADO",
    "Salário Base": 3242.0,
    "Proventos": 4610.4,
    "Vantagens": 0,
    "Vencimentos Totais": 4610.4,
    "Descontos": 365.47,
    "Líquido": 4244.93
  },
  {
    "Matrícula": "00321982 / 1",
    "Tipo da Folha": "Folha Mensal",
    "Nome": "Thiago Gomes Bogado",
    "Cargo": "Agente de Combate as Endemias",
    "Vínculo Empregatício": "CONTRATADO",
    "Salário Base": 3242.0,
    "Proventos": 6359.42,
    "Vantagens": 0,
    "Vencimentos Totais": 6359.42,
    "Descontos": 2431.89,
    "Líquido": 3927.53
  },
  {
    "Matrícula": "00321974 / 1",
    "Tipo da Folha": "Folha Mensal",
    "Nome": "Thiago Thadeu de Souza Dias",
    "Cargo": "Agente de Combate as Endemias",
    "Vínculo Empregatício": "CONTRATADO",
    "Salário Base": 3242.0,
    "Proventos": 5018.43,
    "Vantagens": 0,
    "Vencimentos Totais": 5018.43,
    "Descontos": 355.43,
    "Líquido": 4663.0
  },
  {
    "Matrícula": "00321877 / 1",
    "Tipo da Folha": "Folha Mensal",
    "Nome": "Valquiria Almeida Germano",
    "Cargo": "Agente de Combate as Endemias",
    "Vínculo Empregatício": "CONTRATADO",
    "Salário Base": 3242.0,
    "Proventos": 4610.4,
    "Vantagens": 0,
    "Vencimentos Totais": 4610.4,
    "Descontos": 355.43,
    "Líquido": 4254.97
  },
  {
    "Matrícula": "00321885 / 1",
    "Tipo da Folha": "Folha Mensal",
    "Nome": "Vanessa de Assis Barbosa",
    "Cargo": "Agente de Combate as Endemias",
    "Vínculo Empregatício": "CONTRATADO",
    "Salário Base": 3242.0,
    "Proventos": 5027.59,
    "Vantagens": 0,
    "Vencimentos Totais": 5027.59,
    "Descontos": 1361.29,
    "Líquido": 3666.3
  },
  {
    "Matrícula": "00321893 / 1",
    "Tipo da Folha": "Folha Mensal",
    "Nome": "Vanessa Santos Barreto",
    "Cargo": "Agente de Combate as Endemias",
    "Vínculo Empregatício": "CONTRATADO",
    "Salário Base": 3242.0,
    "Proventos": 4552.79,
    "Vantagens": 0,
    "Vencimentos Totais": 4552.79,
    "Descontos": 447.93,
    "Líquido": 4104.86
  },
  {
    "Matrícula": "00322113 / 1",
    "Tipo da Folha": "Folha Mensal",
    "Nome": "Vania Cristina Caetano dos Santos",
    "Cargo": "Agente de Combate as Endemias",
    "Vínculo Empregatício": "CONTRATADO",
    "Salário Base": 3242.0,
    "Proventos": 4610.4,
    "Vantagens": 0,
    "Vencimentos Totais": 4610.4,
    "Descontos": 355.43,
    "Líquido": 4254.97
  },
  {
    "Matrícula": "00321907 / 1",
    "Tipo da Folha": "Folha Mensal",
    "Nome": "Vania Talita Costa da Silva",
    "Cargo": "Agente de Combate as Endemias",
    "Vínculo Empregatício": "CONTRATADO",
    "Salário Base": 3242.0,
    "Proventos": 5444.78,
    "Vantagens": 0,
    "Vencimentos Totais": 5444.78,
    "Descontos": 355.43,
    "Líquido": 5089.35
  },
  {
    "Matrícula": "00321915 / 1",
    "Tipo da Folha": "Folha Mensal",
    "Nome": "Vera Regina Alves da Silva",
    "Cargo": "Agente de Combate as Endemias",
    "Vínculo Empregatício": "CONTRATADO",
    "Salário Base": 3242.0,
    "Proventos": 4646.4,
    "Vantagens": 0,
    "Vencimentos Totais": 4646.4,
    "Descontos": 355.43,
    "Líquido": 4290.97
  },
  {
    "Matrícula": "00321818 / 1",
    "Tipo da Folha": "Folha Mensal",
    "Nome": "Victor Hugo Rocha Pereira da Silva",
    "Cargo": "Agente de Combate as Endemias",
    "Vínculo Empregatício": "CONTRATADO",
    "Salário Base": 3242.0,
    "Proventos": 5027.59,
    "Vantagens": 0,
    "Vencimentos Totais": 5027.59,
    "Descontos": 1189.38,
    "Líquido": 3838.21
  },
  {
    "Matrícula": "00325724 / 1",
    "Tipo da Folha": "Folha Mensal",
    "Nome": "Viviane de Oliveira Silva Nakanishi",
    "Cargo": "Agente Administrativo",
    "Vínculo Empregatício": "CONTRATADO",
    "Salário Base": 1902.84,
    "Proventos": 3040.03,
    "Vantagens": 0,
    "Vencimentos Totais": 3040.03,
    "Descontos": 146.93,
    "Líquido": 2893.1
  },
  {
    "Matrícula": "00321800 / 1",
    "Tipo da Folha": "Folha Mensal",
    "Nome": "Viviane Oliveira da Silva Bom Heggdorne",
    "Cargo": "Agente de Combate as Endemias",
    "Vínculo Empregatício": "CONTRATADO",
    "Salário Base": 3242.0,
    "Proventos": 4610.4,
    "Vantagens": 0,
    "Vencimentos Totais": 4610.4,
    "Descontos": 355.43,
    "Líquido": 4254.97
  },
  {
    "Matrícula": "00321796 / 1",
    "Tipo da Folha": "Folha Mensal",
    "Nome": "Willian Queiroz Braga",
    "Cargo": "Agente de Combate as Endemias",
    "Vínculo Empregatício": "CONTRATADO",
    "Salário Base": 3242.0,
    "Proventos": 4610.4,
    "Vantagens": 0,
    "Vencimentos Totais": 4610.4,
    "Descontos": 355.43,
    "Líquido": 4254.97
  },
  {
    "Matrícula": "00321788 / 1",
    "Tipo da Folha": "Folha Mensal",
    "Nome": "Yan de Sousa Ferreira",
    "Cargo": "Agente de Combate as Endemias",
    "Vínculo Empregatício": "CONTRATADO",
    "Salário Base": 3242.0,
    "Proventos": 4610.4,
    "Vantagens": 0,
    "Vencimentos Totais": 4610.4,
    "Descontos": 355.43,
    "Líquido": 4254.97
  },
  {
    "Matrícula": "00323225 / 1",
    "Tipo da Folha": "Folha Mensal",
    "Nome": "Zilda Helena Siqueira Sa",
    "Cargo": "Secretario Escolar",
    "Vínculo Empregatício": "CONTRATADO",
    "Salário Base": 1902.84,
    "Proventos": 2514.84,
    "Vantagens": 0,
    "Vencimentos Totais": 2514.84,
    "Descontos": 151.95,
    "Líquido": 2362.89
  }
]